titiler/pgstac/__init__.py
titiler/pgstac/backend.py
titiler/pgstac/db.py
titiler/pgstac/dependencies.py
titiler/pgstac/errors.py
titiler/pgstac/extensions.py
titiler/pgstac/factory.py
titiler/pgstac/logger.py
titiler/pgstac/main.py
titiler/pgstac/model.py
titiler/pgstac/py.typed
titiler/pgstac/reader.py
titiler/pgstac/settings.py
titiler/pgstac/utils.py
titiler/pgstac/templates/conformance.html
titiler/pgstac/templates/footer.html
titiler/pgstac/templates/header.html
titiler/pgstac/templates/landing.html
titiler/pgstac/templates/map.html
titiler_pgstac-2.0.0.dist-info/METADATA
titiler_pgstac-2.0.0.dist-info/WHEEL
titiler_pgstac-2.0.0.dist-info/licenses/LICENSE
titiler_pgstac-2.0.0.dist-info/RECORD
