Metadata-Version: 2.4
Name: titiler-pgstac
Version: 2.0.0
Summary: Connect PgSTAC and TiTiler.
Project-URL: Homepage, https://stac-utils.github.io/titiler-pgstac/
Project-URL: Documentation, https://stac-utils.github.io/titiler-pgstac/
Project-URL: Issues, https://github.com/stac-utils/titiler-pgstac/issues
Project-URL: Source, https://github.com/stac-utils/titiler-pgstac
Project-URL: Changelog, https://stac-utils.github.io/titiler-pgstac/release-notes/
Author-email: Vincent Sarago <vincent@developmentseed.com>, David Bitner <david@developmentseed.com>
License: MIT License
License-File: LICENSE
Keywords: COG,Dynamic tile server,Fastapi,MosaicJSON,STAC,pgSTAC
Classifier: Intended Audience :: Information Technology
Classifier: Intended Audience :: Science/Research
Classifier: License :: OSI Approved :: MIT License
Classifier: Programming Language :: Python :: 3.11
Classifier: Programming Language :: Python :: 3.12
Classifier: Programming Language :: Python :: 3.13
Classifier: Programming Language :: Python :: 3.14
Classifier: Topic :: Scientific/Engineering :: GIS
Requires-Python: >=3.11
Requires-Dist: cql2>=0.3.6
Requires-Dist: pydantic-settings~=2.0
Requires-Dist: pydantic<3.0,>=2.4
Requires-Dist: titiler-core<1.2,>=1.1
Requires-Dist: titiler-extensions<1.2,>=1.1
Requires-Dist: titiler-mosaic<1.2,>=1.1
Provides-Extra: psycopg
Requires-Dist: psycopg[pool]; extra == 'psycopg'
Provides-Extra: psycopg-binary
Requires-Dist: psycopg[binary,pool]; extra == 'psycopg-binary'
Provides-Extra: psycopg-c
Requires-Dist: psycopg[c,pool]; extra == 'psycopg-c'
Provides-Extra: telemetry
Requires-Dist: opentelemetry-api; extra == 'telemetry'
Requires-Dist: opentelemetry-exporter-otlp; extra == 'telemetry'
Requires-Dist: opentelemetry-instrumentation-fastapi; extra == 'telemetry'
Requires-Dist: opentelemetry-instrumentation-logging; extra == 'telemetry'
Requires-Dist: opentelemetry-sdk; extra == 'telemetry'
